odoo8_addon_pos_cash_move_reason-8.0.2.0.0.99.dev3-nspkg.pth
odoo_addons/pos_cash_move_reason/README.rst
odoo_addons/pos_cash_move_reason/__init__.py
odoo_addons/pos_cash_move_reason/__openerp__.py
odoo_addons/pos_cash_move_reason/demo/product_template.xml
odoo_addons/pos_cash_move_reason/i18n/ar.po
odoo_addons/pos_cash_move_reason/i18n/bg.po
odoo_addons/pos_cash_move_reason/i18n/bs.po
odoo_addons/pos_cash_move_reason/i18n/ca.po
odoo_addons/pos_cash_move_reason/i18n/ca_ES.po
odoo_addons/pos_cash_move_reason/i18n/cs.po
odoo_addons/pos_cash_move_reason/i18n/da.po
odoo_addons/pos_cash_move_reason/i18n/de.po
odoo_addons/pos_cash_move_reason/i18n/el_GR.po
odoo_addons/pos_cash_move_reason/i18n/en_GB.po
odoo_addons/pos_cash_move_reason/i18n/es.po
odoo_addons/pos_cash_move_reason/i18n/es_AR.po
odoo_addons/pos_cash_move_reason/i18n/es_CL.po
odoo_addons/pos_cash_move_reason/i18n/es_CO.po
odoo_addons/pos_cash_move_reason/i18n/es_CR.po
odoo_addons/pos_cash_move_reason/i18n/es_DO.po
odoo_addons/pos_cash_move_reason/i18n/es_EC.po
odoo_addons/pos_cash_move_reason/i18n/es_MX.po
odoo_addons/pos_cash_move_reason/i18n/es_PE.po
odoo_addons/pos_cash_move_reason/i18n/es_PY.po
odoo_addons/pos_cash_move_reason/i18n/es_VE.po
odoo_addons/pos_cash_move_reason/i18n/et.po
odoo_addons/pos_cash_move_reason/i18n/eu.po
odoo_addons/pos_cash_move_reason/i18n/fa.po
odoo_addons/pos_cash_move_reason/i18n/fi.po
odoo_addons/pos_cash_move_reason/i18n/fr.po
odoo_addons/pos_cash_move_reason/i18n/fr_CA.po
odoo_addons/pos_cash_move_reason/i18n/gl.po
odoo_addons/pos_cash_move_reason/i18n/he.po
odoo_addons/pos_cash_move_reason/i18n/hr.po
odoo_addons/pos_cash_move_reason/i18n/hr_HR.po
odoo_addons/pos_cash_move_reason/i18n/hu.po
odoo_addons/pos_cash_move_reason/i18n/id.po
odoo_addons/pos_cash_move_reason/i18n/it.po
odoo_addons/pos_cash_move_reason/i18n/ja.po
odoo_addons/pos_cash_move_reason/i18n/ko.po
odoo_addons/pos_cash_move_reason/i18n/lt.po
odoo_addons/pos_cash_move_reason/i18n/lv.po
odoo8_addon_pos_cash_move_reason-8.0.2.0.0.99.dev3.dist-info/METADATA
odoo8_addon_pos_cash_move_reason-8.0.2.0.0.99.dev3.dist-info/WHEEL
odoo8_addon_pos_cash_move_reason-8.0.2.0.0.99.dev3.dist-info/namespace_packages.txt
odoo8_addon_pos_cash_move_reason-8.0.2.0.0.99.dev3.dist-info/top_level.txt
odoo8_addon_pos_cash_move_reason-8.0.2.0.0.99.dev3.dist-info/RECORD
